lecs/__init__.py
lecs/ecs.py
lecs-2.0.0.dist-info/DESCRIPTION.rst
lecs-2.0.0.dist-info/METADATA
lecs-2.0.0.dist-info/RECORD
lecs-2.0.0.dist-info/WHEEL
lecs-2.0.0.dist-info/metadata.json
lecs-2.0.0.dist-info/top_level.txt
